pobatch/__init__.py
pobatch/__main__.py
pobatch/bundles.json
pobatch/geojson2id.py
pobatch/idlist_orders.py
pobatch/mdown.py
pobatch/msize.py
pobatch/pobatch.py
pobatch/text_split.py
pobatch-0.0.8.dist-info/METADATA
pobatch-0.0.8.dist-info/RECORD
pobatch-0.0.8.dist-info/WHEEL
pobatch-0.0.8.dist-info/entry_points.txt
pobatch-0.0.8.dist-info/top_level.txt
