Metadata-Version: 2.1
Name: pobatch
Version: 0.0.8
Summary: porder wrapper for Ordersv2 Batch Client
Home-page: https://github.com/samapriya/pobatch
Author: Samapriya Roy
Author-email: samapriya.roy@gmail.com
License: Apache 2.0
Platform: UNKNOWN
Classifier: Development Status :: 3 - Alpha
Classifier: Intended Audience :: Developers
Classifier: Intended Audience :: Science/Research
Classifier: Natural Language :: English
Classifier: License :: OSI Approved :: Apache Software License
Classifier: Programming Language :: Python
Classifier: Programming Language :: Python :: 2.7
Classifier: Programming Language :: Python :: 3.6
Classifier: Operating System :: OS Independent
Classifier: Topic :: Scientific/Engineering :: GIS
Requires-Dist: requests (>=2.19.1)
Requires-Dist: planet (>=1.2.3)
Requires-Dist: porder (>=0.4.1)
